autoupdater/autoupdater.py
autoupdater78-0.1.0.dist-info/entry_points.txt
autoupdater78-0.1.0.dist-info/LICENSE
autoupdater78-0.1.0.dist-info/METADATA
autoupdater78-0.1.0.dist-info/WHEEL
autoupdater78-0.1.0.dist-info/RECORD
