Metadata-Version: 2.1
Name: autoupdater78
Version: 0.1.0
Summary: Python implementation of AutoUpdater
Home-page: https://github.com/www778878net/AutoUpdater
License: Apache-2.0
Author: frieda
Author-email: www778878net@189.cn
Requires-Python: >=3.9
Classifier: License :: OSI Approved :: Apache Software License
Classifier: Programming Language :: Python :: 3
Classifier: Programming Language :: Python :: 3.9
Classifier: Programming Language :: Python :: 3.10
Classifier: Programming Language :: Python :: 3.11
Classifier: Programming Language :: Python :: 3.12
Requires-Dist: requests (>=2.26.0,<3.0.0)
Project-URL: Documentation, http://www.778878.net/docs/#/autoupdater/
